rdf2srl/__init__.py
rdf2srl/client.py
rdf2srl/http_client.py
rdf2srl/queries.py
rdf2srl/rdfloader.py
rdf2srl/smartloader.py
rdf2srl-1.0.11.dist-info/METADATA
rdf2srl-1.0.11.dist-info/WHEEL
rdf2srl-1.0.11.dist-info/top_level.txt
rdf2srl-1.0.11.dist-info/RECORD
