Metadata-Version: 2.1
Name: rdf2srl
Version: 1.0.11
Summary: Exposes RDF datasets from sparql endpoints for relational learning models in convenient formats
Home-page: https://github.com/aishahasmoh/RDF2SRL
Author: Aisha Mohamed
Author-email: ahmohamed@qf.org.qa
License: UNKNOWN
Platform: UNKNOWN
Classifier: Programming Language :: Python :: 3.5
Requires-Dist: SPARQLWrapper
Requires-Dist: pandas
